sloths/__init__.py
sloths/_stream.py
sloths/_utils.py
sloths/py.typed
sloths/ext/__init__.py
sloths/ext/asyncio.py
sloths/ext/concurrent.py
sloths-0.0.5.dist-info/METADATA
sloths-0.0.5.dist-info/WHEEL
sloths-0.0.5.dist-info/licenses/LICENSE
sloths-0.0.5.dist-info/RECORD
