Metadata-Version: 2.4
Name: sloths
Version: 0.0.5
Summary: Lazy generator pipelines
Project-URL: Homepage, https://github.com/lirsacc/sloths-py
Project-URL: Repository, https://github.com/lirsacc/sloths-py.git
Project-URL: Documentation, https://sloths-py.readthedocs.io/en/latest/
Project-URL: Changelog, https://github.com/lirsacc/sloths-py/blob/main/CHANGELOG.md
Author-email: Charles Lirsac <code@lirsac.com>
License-Expression: MIT
License-File: LICENSE
Classifier: Development Status :: 4 - Beta
Classifier: Intended Audience :: Developers
Classifier: License :: OSI Approved :: MIT License
Classifier: Natural Language :: English
Classifier: Operating System :: OS Independent
Classifier: Programming Language :: Python
Classifier: Programming Language :: Python :: 3 :: Only
Classifier: Programming Language :: Python :: 3.10
Classifier: Programming Language :: Python :: 3.11
Classifier: Programming Language :: Python :: 3.12
Classifier: Programming Language :: Python :: 3.13
Classifier: Topic :: Software Development :: Libraries
Classifier: Topic :: Software Development :: Libraries :: Python Modules
Classifier: Typing :: Typed
Requires-Python: >=3.10
